cratedb_async/__init__.py
cratedb_async/client.py
cratedb_async/response.py
cratedb_async/types.py
cratedb_async-0.0.8.dist-info/METADATA
cratedb_async-0.0.8.dist-info/WHEEL
cratedb_async-0.0.8.dist-info/licenses/LICENSE.md
cratedb_async-0.0.8.dist-info/RECORD
