Metadata-Version: 2.4
Name: cratedb-async
Version: 0.0.8
Summary: Asynchronous http driver for CrateDB
Author-email: surister <surister98@gmail.com>
License: Copyright 2025 github.com/surister
License-File: LICENSE.md
Keywords: connector,cratedb,database,driver,http
Classifier: Development Status :: 4 - Beta
Classifier: Intended Audience :: Developers
Classifier: License :: OSI Approved :: MIT License
Classifier: Natural Language :: English
Classifier: Operating System :: OS Independent
Classifier: Programming Language :: Python
Classifier: Programming Language :: Python :: 3
Classifier: Programming Language :: Python :: 3 :: Only
Classifier: Topic :: Database
Classifier: Topic :: Database :: Front-Ends
Requires-Python: >=3.12
Requires-Dist: httpx[http2]<0.29,>=0.28.1
